{
  "branch_name": "fn-20-feat-020-offer-types-restructure",
  "completion_review_status": "unknown",
  "completion_reviewed_at": null,
  "created_at": "2026-05-15T07:58:36.361160Z",
  "default_impl": null,
  "default_review": null,
  "default_sync": null,
  "depends_on_epics": [],
  "id": "fn-20-feat-020-offer-types-restructure",
  "next_task": 1,
  "plan_review_status": "unknown",
  "plan_reviewed_at": null,
  "spec_path": ".flow/specs/fn-20-feat-020-offer-types-restructure.md",
  "status": "done",
  "title": "FEAT-020 Offer types restructure \u2014 frontend",
  "updated_at": "2026-05-15T10:45:25.422696Z"
}
